{
    "twitter" : {
        "extendedMode" : true,
    	"oauth" : {
            "consumerKey" : "Lb8sTFznrRmuS4OniePGSHXHE",
            "consumerSecret" : "28W7o3702hgvoSK9iysmlLmlfh0ouMBUL00RWG8rV6jcZD8RUg",
            "accessToken" : "58441169-X8s2NbK19FEoEsBnxXh4wqmLqksOaumgivf6TWKiB",
            "accessToken" : "ecret=JMvQypJA1GxqtPqTYXs4Hqx5xRkXNZhnzZtICUPG7Bz92"
    	}
    },
    "tweetwall" : {
        "query" : "#devoxx",
        "title" : "The JavaFX Tweetwall for Devoxx 2017!",
        "stylesheetResource" : "tweetwall.css"
    }
}
